{
  "stocks": [
    {
      "#": 1,
      "symbol": "NABIL",
      "LTP": 725.50,
      "%change": 1.24,
      "open": 716.00,
      "High": 730.00,
      "Low": 715.00,
      "Qty.": 18450,
      "PClose": 716.60,
      "Diff.": 8.90
    },
    {
      "#": 2,
      "symbol": "NLIC",
      "LTP": 1125.00,
      "%change": -0.62,
      "open": 1135.00,
      "High": 1140.00,
      "Low": 1118.00,
      "Qty.": 9400,
      "PClose": 1132.00,
      "Diff.": -7.00
    },
    {
      "#": 3,
      "symbol": "SHIVM",
      "LTP": 435.25,
      "%change": 2.10,
      "open": 427.00,
      "High": 440.00,
      "Low": 425.50,
      "Qty.": 25800,
      "PClose": 426.30,
      "Diff.": 8.95
    },
    {
      "#": 4,
      "symbol": "NTC",
      "LTP": 880.00,
      "%change": 0.91,
      "open": 874.00,
      "High": 888.00,
      "Low": 870.00,
      "Qty.": 13620,
      "PClose": 872.00,
      "Diff.": 8.00
    },
    {
      "#": 5,
      "symbol": "NMB",
      "LTP": 522.50,
      "%change": -0.67,
      "open": 528.00,
      "High": 530.00,
      "Low": 520.00,
      "Qty.": 11600,
      "PClose": 526.00,
      "Diff.": -3.50
    },
    {
      "#": 6,
      "symbol": "NEPSE",
      "LTP": 2100.75,
      "%change": 0.34,
      "open": 2090.00,
      "High": 2115.00,
      "Low": 2085.00,
      "Qty.": 8200,
      "PClose": 2093.60,
      "Diff.": 7.15
    },
    {
      "#": 7,
      "symbol": "HBL",
      "LTP": 398.00,
      "%change": -1.24,
      "open": 405.00,
      "High": 407.00,
      "Low": 395.00,
      "Qty.": 9500,
      "PClose": 403.00,
      "Diff.": -5.00
    },
    {
      "#": 8,
      "symbol": "KBL",
      "LTP": 210.00,
      "%change": 0.96,
      "open": 208.00,
      "High": 212.00,
      "Low": 207.00,
      "Qty.": 12300,
      "PClose": 208.00,
      "Diff.": 2.00
    },
    {
      "#": 9,
      "symbol": "GBIME",
      "LTP": 351.25,
      "%change": 1.15,
      "open": 347.00,
      "High": 354.00,
      "Low": 345.00,
      "Qty.": 17800,
      "PClose": 347.25,
      "Diff.": 4.00
    },
    {
      "#": 10,
      "symbol": "PRVU",
      "LTP": 175.00,
      "%change": -0.57,
      "open": 176.00,
      "High": 178.00,
      "Low": 174.00,
      "Qty.": 14200,
      "PClose": 176.00,
      "Diff.": -1.00
    },
    {
     "#": 11,
      "symbol": "SBI",
      "LTP": 590.50,
      "%change": 1.03,
      "open": 584.00,
      "High": 595.00,
      "Low": 582.00,
      "Qty.": 12600,
      "PClose": 584.50,
      "Diff.": 6.00
    },
    {
      "#": 12,
      "symbol": "MEGA",
      "LTP": 243.75,
      "%change": -0.82,
      "open": 246.00,
      "High": 248.00,
      "Low": 242.00,
      "Qty.": 8700,
      "PClose": 245.75,
      "Diff.": -2.00
    },
    {
      "#": 13,
      "symbol": "NICA",
      "LTP": 672.00,
      "%change": 0.75,
      "open": 667.00,
      "High": 675.00,
      "Low": 662.00,
      "Qty.": 11300,
      "PClose": 667.00,
      "Diff.": 5.00
    },
    {
      "#": 14,
      "symbol": "NCCB",
      "LTP": 165.50,
      "%change": -1.19,
      "open": 168.00,
      "High": 169.00,
      "Low": 164.50,
      "Qty.": 9800,
      "PClose": 167.50,
      "Diff.": -2.00
    },
    {
      "#": 15,
      "symbol": "SRBL",
      "LTP": 189.25,
      "%change": 0.80,
      "open": 188.00,
      "High": 191.00,
      "Low": 186.50,
      "Qty.": 12100,
      "PClose": 187.75,
      "Diff.": 1.50
    },
    {
      "#": 16,
      "symbol": "MBL",
      "LTP": 305.00,
      "%change": 1.16,
      "open": 301.00,
      "High": 307.00,
      "Low": 300.00,
      "Qty.": 10900,
      "PClose": 301.50,
      "Diff.": 3.50
    },
    {
      "#": 17,
      "symbol": "EIC",
      "LTP": 850.00,
      "%change": -0.70,
      "open": 856.00,
      "High": 860.00,
      "Low": 848.00,
      "Qty.": 6400,
      "PClose": 856.00,
      "Diff.": -6.00
    },
    {
      "#": 18,
      "symbol": "API",
      "LTP": 410.75,
      "%change": 0.86,
      "open": 407.00,
      "High": 412.00,
      "Low": 405.50,
      "Qty.": 7800,
      "PClose": 407.25,
      "Diff.": 3.50
    },
    {
      "#": 19,
      "symbol": "UNL",
      "LTP": 1725.00,
      "%change": 0.58,
      "open": 1715.00,
      "High": 1735.00,
      "Low": 1710.00,
      "Qty.": 5200,
      "PClose": 1715.00,
      "Diff.": 10.00
    },
    {
      "#": 20,
      "symbol": "CHCL",
      "LTP": 625.50,
      "%change": -0.95,
      "open": 630.00,
      "High": 632.00,
      "Low": 623.00,
      "Qty.": 10100,
      "PClose": 631.50,
      "Diff.": -6.00
    }
  ]
}
